pyHikUp/HikDeviceGateway.py
pyHikUp/__init__.py
pyHikUp/hik_access_control.py
pyHikUp/hik_connection.py
pyHikUp/hik_dataclasses.py
pyHikUp/hik_device_info.py
pyHikUp/hik_device_management.py
pyHikUp/hik_error.py
pyHikUp/hik_utils.py
pyHikUp-0.1.4.dist-info/LICENSE.txt
pyHikUp-0.1.4.dist-info/METADATA
pyHikUp-0.1.4.dist-info/WHEEL
pyHikUp-0.1.4.dist-info/top_level.txt
pyHikUp-0.1.4.dist-info/RECORD
