Metadata-Version: 2.1
Name: pyHikUp
Version: 0.1.4
Summary: Python wrapper for Hik Device Gateway
Author: John Owen
Maintainer-email: sales@sensoraccess.co.uk
License-File: LICENSE.txt
Requires-Dist: validators
Requires-Dist: requests
Requires-Dist: filetype
